{ "object":
    {
     "height":0,
     "id":1781,
     "name":"",
     "polygon":[
            {
             "x":0,
             "y":0
            }, 
            {
             "x":0,
             "y":-16
            }, 
            {
             "x":16,
             "y":0
            }, 
            {
             "x":48,
             "y":0
            }, 
            {
             "x":48,
             "y":32
            }, 
            {
             "x":16,
             "y":32
            }, 
            {
             "x":0,
             "y":48
            }],
     "rotation":0,
     "type":"rivet",
     "visible":true,
     "width":0,
     "x":4928,
     "y":1328
    },
 "type":"template"
}